watercrawl/__init__.py
watercrawl/api.py
watercrawl/tests.py
watercrawl_py-0.9.2.dist-info/LICENSE
watercrawl_py-0.9.2.dist-info/METADATA
watercrawl_py-0.9.2.dist-info/WHEEL
watercrawl_py-0.9.2.dist-info/top_level.txt
watercrawl_py-0.9.2.dist-info/RECORD
