Metadata-Version: 2.1
Name: watercrawl-py
Version: 0.9.2
Summary: This project used for calling WaterCrawl API in Python
Author-email: AmirMohsen Asaran <info@watercrawl.ai>
Project-URL: Homepage, https://github.com/watercrawl/watercrawl-py
Project-URL: Issues, https://github.com/watercrawl/watercrawl-py/issues
Classifier: Programming Language :: Python :: 3
Classifier: License :: OSI Approved :: MIT License
Classifier: Operating System :: OS Independent
Requires-Python: >=3.8
License-File: LICENSE
Requires-Dist: requests
